vilfo/__init__.py
vilfo/client.py
vilfo/exceptions.py
vilfo_api_client-0.5.0.dist-info/LICENSE
vilfo_api_client-0.5.0.dist-info/METADATA
vilfo_api_client-0.5.0.dist-info/WHEEL
vilfo_api_client-0.5.0.dist-info/top_level.txt
vilfo_api_client-0.5.0.dist-info/RECORD
