Metadata-Version: 2.1
Name: vilfo-api-client
Version: 0.5.0
Summary: Simple wrapper client for the Vilfo router API
Home-page: https://github.com/mannew/vilfo-api-client-python
Author: Emanuel Winblad
Author-email: winblad@protonmail.com
License: MIT License
Keywords: vilfo,router
License-File: LICENSE
Requires-Dist: getmac
Requires-Dist: requests
Requires-Dist: semver
Provides-Extra: dev
Requires-Dist: responses; extra == "dev"
Provides-Extra: test
Requires-Dist: responses; extra == "test"
